Workbook

Sheet README
A1: Polish Corporate GHG Benchmark (ESRS E1, reporting year 2025)
A3: Purpose
A4: Collect, consolidate and validate climate data from the first ESRS sustainability statements of Polish listed companies, normalise units, and calculate comparable emission-intensity indicators.
A6: Workflow
A7: 1. Input_Data: one row per company. Type values exactly as reported and choose the reported unit from the dropdowns. Blue text = input.
A8: 2. Units: conversion factors to base units (tCO2e, PLN m, MWh). Only the EUR/PLN rate is an input.
A9: 3. Calculations: normalised values and KPIs, all formula-driven. Do not type here.
A10: 4. Data_Quality: automatic checks per company plus a manual issue log.
A11: 5. Power Query: load the tables Input_Data and Units, merge on unit, recreate the conversions, and check the result matches the Calculations sheet.
A12: 6. Dashboard: load the Calculations sheet into Tableau Public or Power BI.
A14: Where to find the data in an ESRS report
A15: Scope 1, 2 (location- and market-based), 3: disclosure E1-6 'Gross Scopes 1, 2, 3 and Total GHG emissions' table.
... A27: Row 2 of Input_Data is a fictional example showing the format. Delete it or overwrite it once real data is entered.

Sheet Units
A1: Assumption
A2: EUR/PLN average rate for the reporting year (verify on NBP) | B2: 4.3
A4: Unit | B4: Type | C4: Factor_to_Base
A5: tCO2e | B5: GHG | C5: 1
A6: ktCO2e | B6: GHG | C6: 1000
A7: MtCO2e | B7: GHG | C7: 1000000
A8: PLN thousand | B8: Revenue | C8: 0.001
A9: PLN million | B9: Revenue | C9: 1
A10: EUR thousand | B10: Revenue | C10: =$B$2/1000 -> 0.0043
A11: EUR million | B11: Revenue | C11: =$B$2 -> 4.3
A12: MWh | B12: Energy | C12: 1
A13: GWh | B13: Energy | C13: 1000
A14: GJ | B14: Energy | C14: =1/3.6 -> 0.27777778
A15: TJ | B15: Energy | C15: =1000/3.6 -> 277.77778
A16: tCO2e / PLN million | B16: Intensity | C16: 1
A17: tCO2e / PLN thousand | B17: Intensity | C17: 1000
A18: tCO2e / EUR million | B18: Intensity | C18: =1/$B$2 -> 0.23255814
A19: tCO2e / EUR thousand | B19: Intensity | C19: =1000/$B$2 -> 232.55814
A21: Base units: tCO2e (GHG), PLN million (revenue), MWh (energy), tCO2e per PLN million (intensity).

Sheet Units1
A1: Unit | B1: Type | C1: Factor_to_Base
A2: tCO2e | B2: GHG | C2: 1
A3: ktCO2e | B3: GHG | C3: 1000
A4: MtCO2e | B4: GHG | C4: 1000000
A5: PLN thousand | B5: Revenue | C5: 0.001
A6: PLN million | B6: Revenue | C6: 1
A7: EUR thousand | B7: Revenue | C7: 0.0043
A8: EUR million | B8: Revenue | C8: 4.3
A9: MWh | B9: Energy | C9: 1
A10: GWh | B10: Energy | C10: 1000
A11: GJ | B11: Energy | C11: 0.27777778
A12: TJ | B12: Energy | C12: 277.77778
A13: tCO2e / PLN million | B13: Intensity | C13: 1
... A16: tCO2e / EUR thousand | B16: Intensity | C16: 232.55814

Sheet PQ_Output
A1: Company_ID | B1: Company | C1: Sector | D1: Total_MB_t | E1: Revenue_PLNm | F1: Intensity_PQ | G1: Energy_Intensity_PQ | H1: Check_vs_Formula
A2: PGE | B2: PGE Polska Grupa Energetyczna | C2: Energy utilities | D2: 77405240 | E2: 61434 | F2: 1259.974 | G2: 2433.4048 | H2: =ROUND(F2-_xlfn.XLOOKUP(A2,Calculations!A:A,Calculations!L:L),6) -> 0
A3: TPE | B3: Tauron Polska Energia | C3: Energy utilities | D3: 26848613 | E3: 33277 | F3: 806.82192 | G3: 939.21042 | H3: =ROUND(F3-_xlfn.XLOOKUP(A3,Calculations!A:A,Calculations!L:L),6) -> 0
A4: KTY | B4: Grupa Kety | C4: Industrial manufacturing | D4: 1340613 | E4: 5494.6 | F4: 243.98737 | G4: 75.963899 | H4: =ROUND(F4-_xlfn.XLOOKUP(A4,Calculations!A:A,Calculations!L:L),6) -> 0
A5: DNP | B5: Dino Polska | C5: Food retail | D5: 7323236 | E5: 33634.155 | F5: 217.73212 | G5: 12.153568 | H5: =ROUND(F5-_xlfn.XLOOKUP(A5,Calculations!A:A,Calculations!L:L),6) -> 0
A6: KGH | B6: KGHM Polska Miedz | C6: Metals and mining | D6: 6701474 | E6: 36342.35 | F6: 184.39848 | G6: 220.19305 | H6: =ROUND(F6-_xlfn.XLOOKUP(A6,Calculations!A:A,Calculations!L:L),6) -> 0
A7: ZAB | B7: Grupa Zabka | C7: Food retail | D7: 3419668 | E7: 27153 | F7: 125.94071 | G7: 5.0656649 | H7: =ROUND(F7-_xlfn.XLOOKUP(A7,Calculations!A:A,Calculations!L:L),6) -> 0
A8: OPL | B8: Orange Polska | C8: Telecommunications | D8: 522050 | E8: 13133 | F8: 39.751009 | G8: 41.707759 | H8: =ROUND(F8-_xlfn.XLOOKUP(A8,Calculations!A:A,Calculations!L:L),6) -> 0
A9: ALE | B9: Allegro.eu | C9: E-commerce | D9: 425372 | E9: 11885.8 | F9: 35.788252 | G9: 3.6684952 | H9: =ROUND(F9-_xlfn.XLOOKUP(A9,Calculations!A:A,Calculations!L:L),6) -> 0

Sheet Input_Data
A1: Company_ID | B1: Company | C1: Sector | D1: Reporting_Period | E1: Scope1 | F1: Scope2_LB | G1: Scope2_MB | H1: Scope3 | I1: GHG_Unit | J1: Net_Revenue | K1: Revenue_Unit | L1: Employees | M1: Employee_Basis | N1: Energy_Consumption | O1: Energy_Unit | P1: Reported_GHG_Intensity_MB | Q1: Intensity_Unit | R1: Taxonomy_Turnover_Aligned | S1: Taxonomy_CapEx_Aligned | T1: Taxonomy_OpEx_Aligned | U1: Source_Pages | V1: Notes
A3: PGE | B3: PGE Polska Grupa Energetyczna | C3: Energy utilities | D3: FY2025 | E3: 52200270 | F3: 1297281 | G3: 1297281 | H3: 23907689 | I3: tCO2e | J3: 61434 | K3: PLN million | L3: 41690 | M3: Headcount | N3: 149493791 | O3: MWh | P3: 1300 | Q3: tCO2e / PLN million | R3: 0.246 | S3: 0.429 | T3: 0.412 | U3: Management Board report 2025 (unofficial PDF): E1-6 table p.258; intensity p.259; E1-5 p.~256; S1-6 section 9.3.1.8; Taxonomy KPI summary; revenue key financial data p.7 | V3: Reported intensity 0.0013 t/PLN converted to 1,300 t/PLN m. Scope 1 98.98% under EU ETS. Employees = headcount at year end (average 42,329).
A4: TPE | B4: Tauron Polska Energia | C4: Energy utilities | D4: FY2025 | E4: 9825368 | F4: 1118942 | G4: 962262 | H4: 16060983 | I4: tCO2e | J4: 33277 | K4: PLN million | L4: 19267 | M4: Headcount | N4: 31254105 | O4: MWh | P4: 807 | Q4: tCO2e / PLN million | R4: 0.388 | S4: 0.845 | T4: 0.742 | U4: Management report 2025 (SprZarzadu): E1-6 Table 137 p.317-318; intensity Table 138; E1-5 energy table; S1-6 Table 168; Taxonomy KPI templates | V4: Reported intensity 0.000807 t/PLN converted to 807 t/PLN m. Revenue = intensity denominator 33,277 PLN m (Przychody ze sprzedazy). Scope 1 98% under EU ETS.
A5: KGH | B5: KGHM Polska Miedz | C5: Metals and mining | D5: FY2025 | E5: 2068510 | F5: 1554657 | G5: 2105896 | H5: 2527068 | I5: tCO2e | J5: 36342.35 | K5: PLN million | L5: 34477 | M5: Headcount | N5: 8002333 | O5: MWh | P5: 184.398 | Q5: tCO2e / PLN million | R5: 0 | S5: 0 | T5: 0 | U5: Management Board report 2025: E1-6 Table 126 (Group) p.231; intensity Table 127; E1-5 p.229-230; S1-6 Table 143 p.274; Taxonomy summary KPIs | V5: Group table used (Table 125 = parent company only). Scope 1 77.9% under EU ETS. Taxonomy alignment not assessed in 2025. Limited assurance.
A6: KTY | B6: Grupa Kety | C6: Industrial manufacturing | D6: FY2025 | E6: 41938 | F6: 112196 | G6: 118957 | H6: 1179718 | I6: tCO2e | J6: 5494.6 | K6: PLN million | L6: 6240 | M6: Headcount | N6: 417391.24 | O6: MWh | R6: 0.255 | S6: 0.086 | T6: 0.38 | U6: Sustainability statement 2025: E1-6 Table 50 p.42; intensity Table 53 p.46-47; E1-5 energy table; S1-6 p.~60; Taxonomy Table 43 | V6: Only location-based intensity disclosed (242.7 t/PLN m), so MB check not possible; LB recomputed 242.8 matches. Revenue = Taxonomy denominator 5,494.6 PLN m. Average employment 6,251.
A7: ZAB | B7: Grupa Zabka | C7: Food retail | D7: FY2025 | E7: 25082 | F7: 24890 | G7: 7478 | H7: 3387108 | I7: tCO2e | J7: 27153 | K7: PLN million | L7: 4257 | M7: Headcount | N7: 137548 | O7: MWh | P7: 125.9 | Q7: tCO2e / PLN million | R7: 0 | S7: 0.082 | T7: 0 | U7: Annual Report 2025: E1-6 p.135-136 (Group table); intensity (Group) E1; energy E1-5 p.134-135; S1-6 p.137; Taxonomy summary KPIs | V7: Group level (Zabka Polska also disclosed separately). Franchise model: store electricity in Scope 3 cat. 14. Taxonomy OpEx not material (exemption). Limited assurance.
A8: DNP | B8: Dino Polska | C8: Food retail | D8: FY2025 | E8: 41804 | F8: 135019 | G8: 207858 | H8: 7073574 | I8: tCO2e | J8: 33634155 | K8: PLN thousand | L8: 55856 | M8: Headcount | N8: 408775 | O8: MWh | P8: 217.7 | Q8: tCO2e / PLN million | R8: 0 | S8: 0 | T8: 0 | U8: E1-6 p.73; intensity p.75; E1-5 p.72; employees p.58/84; Taxonomy p.66-69 | V8: Revenue = consolidated sales. Employees = headcount at 31.12.2025 (S1-6). Taxonomy: turnover not assessed (exemption), CapEx eligible 38.9% aligned 0%, OpEx 0%. Limited assurance by KPMG.
A9: OPL | B9: Orange Polska | C9: Telecommunications | D9: FY2025 | E9: 21538 | F9: 272838 | G9: 7354 | H9: 493158 | I9: tCO2e | J9: 13133 | K9: PLN million | L9: 8172 | M9: Headcount | N9: 547748 | O9: MWh | P9: 40 | Q9: tCO2e / PLN million | R9: 0 | S9: 0 | T9: 0 | U9: E1-6 p.122 ; E1-5 P.121 ; Intensity p.123 ; Employees p.143 ; Taxonomy p.173 | V9: Group level. Revenue PLN 13,133m (consolidated). Taxonomy alignment not assessed (materiality exemption, Reg. 2026/73). FTE 7,793.
A10: ALE | B10: Allegro.eu | C10: E-commerce | D10: FY2025 | E10: 1803 | F10: 17739 | G10: 4017 | H10: 419552 | I10: tCO2e | J10: 11885.8 | K10: PLN million | L10: 6090 | M10: Headcount | N10: 43603 | O10: MWh | P10: 35.1 | Q10: tCO2e / PLN million | R10: 1e-05 | S10: 0.339 | T10: 0.404 | U10: E1.3/E1.6 (E1-6); intensity E1.13; energy E1.1; employees S1.3; Taxonomy summary; revenue p.384 + note 18.2 p.428 | V10: Group boundary (not Polish Operations). Revenue = continuing 11,458.1 + discontinued Mall South 427.7 (PLN m). Taxonomy turnover aligned 0.001%. Limited assurance.

Sheet Calculations
A1: Company_ID | B1: Company | C1: Sector | D1: Scope1_t | E1: Scope2_LB_t | F1: Scope2_MB_t | G1: Scope3_t | H1: Total_S12_MB_t | I1: Total_S123_MB_t | J1: Revenue_PLNm | K1: Intensity_S12_MB (t/PLN m) | L1: Intensity_S123_MB (t/PLN m) | M1: S12_MB_per_Employee (t) | N1: Scope3_Share | O1: Energy_MWh | P1: Energy_Intensity (MWh/PLN m) | Q1: Reported_Intensity (t/PLN m) | R1: Intensity_Deviation | S1: Taxonomy_Turnover | T1: Taxonomy_CapEx | U1: Taxonomy_OpEx
A2: =IF(Input_Data!A2="","",Input_Data!A2) | B2: =IF(Input_Data!B2="","",Input_Data!B2) | C2: =IF(Input_Data!C2="","",Input_Data!C2) | D2: =IF(OR(Input_Data!E2="",Input_Data!I2=""),"",Input_Data!E2*INDEX(Units!$C$5:$C$19,MATCH(Input_Data!$I2,Units!$A$5:$A$19,0))) | E2: =IF(OR(Input_Data!F2="",Input_Data!I2=""),"",Input_Data!F2*INDEX(Units!$C$5:$C$19,MATCH(Input_Data!$I2,Units!$A$5:$A$19,0))) | F2: =IF(OR(Input_Data!G2="",Input_Data!I2=""),"",Input_Data!G2*INDEX(Units!$C$5:$C$19,MATCH(Input_Data!$I2,Units!$A$5:$A$19,0))) | G2: =IF(OR(Input_Data!H2="",Input_Data!I2=""),"",Input_Data!H2*INDEX(Units!$C$5:$C$19,MATCH(Input_Data!$I2,Units!$A$5:$A$19,0))) | H2: =IF(OR(D2="",F2=""),"",D2+F2) | I2: =IF(OR(H2="",G2=""),"",H2+G2) | J2: =IF(OR(Input_Data!J2="",Input_Data!K2=""),"",Input_Data!J2*INDEX(Units!$C$5:$C$19,MATCH(Input_Data!$K2,Units!$A$5:$A$19,0))) | K2: =IF(OR(H2="",J2=""),"",H2/J2) | L2: =IF(OR(I2="",J2=""),"",I2/J2) | M2: =IF(OR(H2="",Input_Data!L2=""),"",H2/Input_Data!L2) | N2: =IF(OR(G2="",I2=""),"",G2/I2) | O2: =IF(OR(Input_Data!N2="",Input_Data!O2=""),"",Input_Data!N2*INDEX(Units!$C$5:$C$19,MATCH(Input_Data!$O2,Units!$A$5:$A$19,0))) | P2: =IF(OR(O2="",J2=""),"",O2/J2) | Q2: =IF(OR(Input_Data!P2="",Input_Data!Q2=""),"",Input_Data!P2*INDEX(Units!$C$5:$C$19,MATCH(Input_Data!$Q2,Units!$A$5:$A$19,0))) | R2: =IF(OR(L2="",Q2=""),"",L2/Q2-1) | S2: =IF(Input_Data!R2="","",Input_Data!R2) | T2: =IF(Input_Data!S2="","",Input_Data!S2) | U2: =IF(Input_Data!T2="","",Input_Data!T2)
A3: =IF(Input_Data!A3="","",Input_Data!A3) -> PGE | B3: =IF(Input_Data!B3="","",Input_Data!B3) -> PGE Polska Grupa Energetyczna | C3: =IF(Input_Data!C3="","",Input_Data!C3) -> Energy utilities | D3: =IF(OR(Input_Data!E3="",Input_Data!I3=""),"",Input_Data!E3*INDEX(Units!$C$5:$C$19,MATCH(Input_Data!$I3,Units!$A$5:$A$19,0))) -> 52200270 | E3: =IF(OR(Input_Data!F3="",Input_Data!I3=""),"",Input_Data!F3*INDEX(Units!$C$5:$C$19,MATCH(Input_Data!$I3,Units!$A$5:$A$19,0))) -> 1297281 | F3: =IF(OR(Input_Data!G3="",Input_Data!I3=""),"",Input_Data!G3*INDEX(Units!$C$5:$C$19,MATCH(Input_Data!$I3,Units!$A$5:$A$19,0))) -> 1297281 | G3: =IF(OR(Input_Data!H3="",Input_Data!I3=""),"",Input_Data!H3*INDEX(Units!$C$5:$C$19,MATCH(Input_Data!$I3,Units!$A$5:$A$19,0))) -> 23907689 | H3: =IF(OR(D3="",F3=""),"",D3+F3) -> 53497551 | I3: =IF(OR(H3="",G3=""),"",H3+G3) -> 77405240 | J3: =IF(OR(Input_Data!J3="",Input_Data!K3=""),"",Input_Data!J3*INDEX(Units!$C$5:$C$19,MATCH(Input_Data!$K3,Units!$A$5:$A$19,0))) -> 61434 | K3: =IF(OR(H3="",J3=""),"",H3/J3) -> 870.81341 | L3: =IF(OR(I3="",J3=""),"",I3/J3) -> 1259.974 | M3: =IF(OR(H3="",Input_Data!L3=""),"",H3/Input_Data!L3) -> 1283.2226 | N3: =IF(OR(G3="",I3=""),"",G3/I3) -> 0.30886396 | O3: =IF(OR(Input_Data!N3="",Input_Data!O3=""),"",Input_Data!N3*INDEX(Units!$C$5:$C$19,MATCH(Input_Data!$O3,Units!$A$5:$A$19,0))) -> 149493791 | P3: =IF(OR(O3="",J3=""),"",O3/J3) -> 2433.4048 | Q3: =IF(OR(Input_Data!P3="",Input_Data!Q3=""),"",Input_Data!P3*INDEX(Units!$C$5:$C$19,MATCH(Input_Data!$Q3,Units!$A$5:$A$19,0))) -> 1300 | R3: =IF(OR(L3="",Q3=""),"",L3/Q3-1) -> -0.030789265 | S3: =IF(Input_Data!R3="","",Input_Data!R3) -> 0.246 | T3: =IF(Input_Data!S3="","",Input_Data!S3) -> 0.429 | U3: =IF(Input_Data!T3="","",Input_Data!T3) -> 0.412
A4: =IF(Input_Data!A4="","",Input_Data!A4) -> TPE | B4: =IF(Input_Data!B4="","",Input_Data!B4) -> Tauron Polska Energia | C4: =IF(Input_Data!C4="","",Input_Data!C4) -> Energy utilities | D4: =IF(OR(Input_Data!E4="",Input_Data!I4=""),"",Input_Data!E4*INDEX(Units!$C$5:$C$19,MATCH(Input_Data!$I4,Units!$A$5:$A$19,0))) -> 9825368 | E4: =IF(OR(Input_Data!F4="",Input_Data!I4=""),"",Input_Data!F4*INDEX(Units!$C$5:$C$19,MATCH(Input_Data!$I4,Units!$A$5:$A$19,0))) -> 1118942 | F4: =IF(OR(Input_Data!G4="",Input_Data!I4=""),"",Input_Data!G4*INDEX(Units!$C$5:$C$19,MATCH(Input_Data!$I4,Units!$A$5:$A$19,0))) -> 962262 | G4: =IF(OR(Input_Data!H4="",Input_Data!I4=""),"",Input_Data!H4*INDEX(Units!$C$5:$C$19,MATCH(Input_Data!$I4,Units!$A$5:$A$19,0))) -> 16060983 | H4: =IF(OR(D4="",F4=""),"",D4+F4) -> 10787630 | I4: =IF(OR(H4="",G4=""),"",H4+G4) -> 26848613 | J4: =IF(OR(Input_Data!J4="",Input_Data!K4=""),"",Input_Data!J4*INDEX(Units!$C$5:$C$19,MATCH(Input_Data!$K4,Units!$A$5:$A$19,0))) -> 33277 | K4: =IF(OR(H4="",J4=""),"",H4/J4) -> 324.17676 | L4: =IF(OR(I4="",J4=""),"",I4/J4) -> 806.82192 | M4: =IF(OR(H4="",Input_Data!L4=""),"",H4/Input_Data!L4) -> 559.9019 | N4: =IF(OR(G4="",I4=""),"",G4/I4) -> 0.59820532 | O4: =IF(OR(Input_Data!N4="",Input_Data!O4=""),"",Input_Data!N4*INDEX(Units!$C$5:$C$19,MATCH(Input_Data!$O4,Units!$A$5:$A$19,0))) -> 31254105 | P4: =IF(OR(O4="",J4=""),"",O4/J4) -> 939.21042 | Q4: =IF(OR(Input_Data!P4="",Input_Data!Q4=""),"",Input_Data!P4*INDEX(Units!$C$5:$C$19,MATCH(Input_Data!$Q4,Units!$A$5:$A$19,0))) -> 807 | R4: =IF(OR(L4="",Q4=""),"",L4/Q4-1) -> -0.00022067033 | S4: =IF(Input_Data!R4="","",Input_Data!R4) -> 0.388 | T4: =IF(Input_Data!S4="","",Input_Data!S4) -> 0.845 | U4: =IF(Input_Data!T4="","",Input_Data!T4) -> 0.742
A5: =IF(Input_Data!A5="","",Input_Data!A5) -> KGH | B5: =IF(Input_Data!B5="","",Input_Data!B5) -> KGHM Polska Miedz | C5: =IF(Input_Data!C5="","",Input_Data!C5) -> Metals and mining | D5: =IF(OR(Input_Data!E5="",Input_Data!I5=""),"",Input_Data!E5*INDEX(Units!$C$5:$C$19,MATCH(Input_Data!$I5,Units!$A$5:$A$19,0))) -> 2068510 | E5: =IF(OR(Input_Data!F5="",Input_Data!I5=""),"",Input_Data!F5*INDEX(Units!$C$5:$C$19,MATCH(Input_Data!$I5,Units!$A$5:$A$19,0))) -> 1554657 | F5: =IF(OR(Input_Data!G5="",Input_Data!I5=""),"",Input_Data!G5*INDEX(Units!$C$5:$C$19,MATCH(Input_Data!$I5,Units!$A$5:$A$19,0))) -> 2105896 | G5: =IF(OR(Input_Data!H5="",Input_Data!I5=""),"",Input_Data!H5*INDEX(Units!$C$5:$C$19,MATCH(Input_Data!$I5,Units!$A$5:$A$19,0))) -> 2527068 | H5: =IF(OR(D5="",F5=""),"",D5+F5) -> 4174406 | I5: =IF(OR(H5="",G5=""),"",H5+G5) -> 6701474 | J5: =IF(OR(Input_Data!J5="",Input_Data!K5=""),"",Input_Data!J5*INDEX(Units!$C$5:$C$19,MATCH(Input_Data!$K5,Units!$A$5:$A$19,0))) -> 36342.35 | K5: =IF(OR(H5="",J5=""),"",H5/J5) -> 114.8634 | L5: =IF(OR(I5="",J5=""),"",I5/J5) -> 184.39848 | M5: =IF(OR(H5="",Input_Data!L5=""),"",H5/Input_Data!L5) -> 121.07799 | N5: =IF(OR(G5="",I5=""),"",G5/I5) -> 0.37709137 | O5: =IF(OR(Input_Data!N5="",Input_Data!O5=""),"",Input_Data!N5*INDEX(Units!$C$5:$C$19,MATCH(Input_Data!$O5,Units!$A$5:$A$19,0))) -> 8002333 | P5: =IF(OR(O5="",J5=""),"",O5/J5) -> 220.19305 | Q5: =IF(OR(Input_Data!P5="",Input_Data!Q5=""),"",Input_Data!P5*INDEX(Units!$C$5:$C$19,MATCH(Input_Data!$Q5,Units!$A$5:$A$19,0))) -> 184.398 | R5: =IF(OR(L5="",Q5=""),"",L5/Q5-1) -> 2.5881985e-06 | S5: =IF(Input_Data!R5="","",Input_Data!R5) -> 0 | T5: =IF(Input_Data!S5="","",Input_Data!S5) -> 0 | U5: =IF(Input_Data!T5="","",Input_Data!T5) -> 0
A6: =IF(Input_Data!A6="","",Input_Data!A6) -> KTY | B6: =IF(Input_Data!B6="","",Input_Data!B6) -> Grupa Kety | C6: =IF(Input_Data!C6="","",Input_Data!C6) -> Industrial manufacturing | D6: =IF(OR(Input_Data!E6="",Input_Data!I6=""),"",Input_Data!E6*INDEX(Units!$C$5:$C$19,MATCH(Input_Data!$I6,Units!$A$5:$A$19,0))) -> 41938 | E6: =IF(OR(Input_Data!F6="",Input_Data!I6=""),"",Input_Data!F6*INDEX(Units!$C$5:$C$19,MATCH(Input_Data!$I6,Units!$A$5:$A$19,0))) -> 112196 | F6: =IF(OR(Input_Data!G6="",Input_Data!I6=""),"",Input_Data!G6*INDEX(Units!$C$5:$C$19,MATCH(Input_Data!$I6,Units!$A$5:$A$19,0))) -> 118957 | G6: =IF(OR(Input_Data!H6="",Input_Data!I6=""),"",Input_Data!H6*INDEX(Units!$C$5:$C$19,MATCH(Input_Data!$I6,Units!$A$5:$A$19,0))) -> 1179718 | H6: =IF(OR(D6="",F6=""),"",D6+F6) -> 160895 | I6: =IF(OR(H6="",G6=""),"",H6+G6) -> 1340613 | J6: =IF(OR(Input_Data!J6="",Input_Data!K6=""),"",Input_Data!J6*INDEX(Units!$C$5:$C$19,MATCH(Input_Data!$K6,Units!$A$5:$A$19,0))) -> 5494.6 | K6: =IF(OR(H6="",J6=""),"",H6/J6) -> 29.282386 | L6: =IF(OR(I6="",J6=""),"",I6/J6) -> 243.98737 | M6: =IF(OR(H6="",Input_Data!L6=""),"",H6/Input_Data!L6) -> 25.784455 | N6: =IF(OR(G6="",I6=""),"",G6/I6) -> 0.87998401 | O6: =IF(OR(Input_Data!N6="",Input_Data!O6=""),"",Input_Data!N6*INDEX(Units!$C$5:$C$19,MATCH(Input_Data!$O6,Units!$A$5:$A$19,0))) -> 417391.24 | P6: =IF(OR(O6="",J6=""),"",O6/J6) -> 75.963899 | Q6: =IF(OR(Input_Data!P6="",Input_Data!Q6=""),"",Input_Data!P6*INDEX(Units!$C$5:$C$19,MATCH(Input_Data!$Q6,Units!$A$5:$A$19,0))) | R6: =IF(OR(L6="",Q6=""),"",L6/Q6-1) | S6: =IF(Input_Data!R6="","",Input_Data!R6) -> 0.255 | T6: =IF(Input_Data!S6="","",Input_Data!S6) -> 0.086 | U6: =IF(Input_Data!T6="","",Input_Data!T6) -> 0.38
A7: =IF(Input_Data!A7="","",Input_Data!A7) -> ZAB | B7: =IF(Input_Data!B7="","",Input_Data!B7) -> Grupa Zabka | C7: =IF(Input_Data!C7="","",Input_Data!C7) -> Food retail | D7: =IF(OR(Input_Data!E7="",Input_Data!I7=""),"",Input_Data!E7*INDEX(Units!$C$5:$C$19,MATCH(Input_Data!$I7,Units!$A$5:$A$19,0))) -> 25082 | E7: =IF(OR(Input_Data!F7="",Input_Data!I7=""),"",Input_Data!F7*INDEX(Units!$C$5:$C$19,MATCH(Input_Data!$I7,Units!$A$5:$A$19,0))) -> 24890 | F7: =IF(OR(Input_Data!G7="",Input_Data!I7=""),"",Input_Data!G7*INDEX(Units!$C$5:$C$19,MATCH(Input_Data!$I7,Units!$A$5:$A$19,0))) -> 7478 | G7: =IF(OR(Input_Data!H7="",Input_Data!I7=""),"",Input_Data!H7*INDEX(Units!$C$5:$C$19,MATCH(Input_Data!$I7,Units!$A$5:$A$19,0))) -> 3387108 | H7: =IF(OR(D7="",F7=""),"",D7+F7) -> 32560 | I7: =IF(OR(H7="",G7=""),"",H7+G7) -> 3419668 | J7: =IF(OR(Input_Data!J7="",Input_Data!K7=""),"",Input_Data!J7*INDEX(Units!$C$5:$C$19,MATCH(Input_Data!$K7,Units!$A$5:$A$19,0))) -> 27153 | K7: =IF(OR(H7="",J7=""),"",H7/J7) -> 1.1991309 | L7: =IF(OR(I7="",J7=""),"",I7/J7) -> 125.94071 | M7: =IF(OR(H7="",Input_Data!L7=""),"",H7/Input_Data!L7) -> 7.6485788 | N7: =IF(OR(G7="",I7=""),"",G7/I7) -> 0.99047861 | O7: =IF(OR(Input_Data!N7="",Input_Data!O7=""),"",Input_Data!N7*INDEX(Units!$C$5:$C$19,MATCH(Input_Data!$O7,Units!$A$5:$A$19,0))) -> 137548 | P7: =IF(OR(O7="",J7=""),"",O7/J7) -> 5.0656649 | Q7: =IF(OR(Input_Data!P7="",Input_Data!Q7=""),"",Input_Data!P7*INDEX(Units!$C$5:$C$19,MATCH(Input_Data!$Q7,Units!$A$5:$A$19,0))) -> 125.9 | R7: =IF(OR(L7="",Q7=""),"",L7/Q7-1) -> 0.00032332302 | S7: =IF(Input_Data!R7="","",Input_Data!R7) -> 0 | T7: =IF(Input_Data!S7="","",Input_Data!S7) -> 0.082 | U7: =IF(Input_Data!T7="","",Input_Data!T7) -> 0
A8: =IF(Input_Data!A8="","",Input_Data!A8) -> DNP | B8: =IF(Input_Data!B8="","",Input_Data!B8) -> Dino Polska | C8: =IF(Input_Data!C8="","",Input_Data!C8) -> Food retail | D8: =IF(OR(Input_Data!E8="",Input_Data!I8=""),"",Input_Data!E8*INDEX(Units!$C$5:$C$19,MATCH(Input_Data!$I8,Units!$A$5:$A$19,0))) -> 41804 | E8: =IF(OR(Input_Data!F8="",Input_Data!I8=""),"",Input_Data!F8*INDEX(Units!$C$5:$C$19,MATCH(Input_Data!$I8,Units!$A$5:$A$19,0))) -> 135019 | F8: =IF(OR(Input_Data!G8="",Input_Data!I8=""),"",Input_Data!G8*INDEX(Units!$C$5:$C$19,MATCH(Input_Data!$I8,Units!$A$5:$A$19,0))) -> 207858 | G8: =IF(OR(Input_Data!H8="",Input_Data!I8=""),"",Input_Data!H8*INDEX(Units!$C$5:$C$19,MATCH(Input_Data!$I8,Units!$A$5:$A$19,0))) -> 7073574 | H8: =IF(OR(D8="",F8=""),"",D8+F8) -> 249662 | I8: =IF(OR(H8="",G8=""),"",H8+G8) -> 7323236 | J8: =IF(OR(Input_Data!J8="",Input_Data!K8=""),"",Input_Data!J8*INDEX(Units!$C$5:$C$19,MATCH(Input_Data!$K8,Units!$A$5:$A$19,0))) -> 33634.155 | K8: =IF(OR(H8="",J8=""),"",H8/J8) -> 7.4228712 | L8: =IF(OR(I8="",J8=""),"",I8/J8) -> 217.73212 | M8: =IF(OR(H8="",Input_Data!L8=""),"",H8/Input_Data!L8) -> 4.4697436 | N8: =IF(OR(G8="",I8=""),"",G8/I8) -> 0.96590824 | O8: =IF(OR(Input_Data!N8="",Input_Data!O8=""),"",Input_Data!N8*INDEX(Units!$C$5:$C$19,MATCH(Input_Data!$O8,Units!$A$5:$A$19,0))) -> 408775 | P8: =IF(OR(O8="",J8=""),"",O8/J8) -> 12.153568 | Q8: =IF(OR(Input_Data!P8="",Input_Data!Q8=""),"",Input_Data!P8*INDEX(Units!$C$5:$C$19,MATCH(Input_Data!$Q8,Units!$A$5:$A$19,0))) -> 217.7 | R8: =IF(OR(L8="",Q8=""),"",L8/Q8-1) -> 0.00014755989 | S8: =IF(Input_Data!R8="","",Input_Data!R8) -> 0 | T8: =IF(Input_Data!S8="","",Input_Data!S8) -> 0 | U8: =IF(Input_Data!T8="","",Input_Data!T8) -> 0
A9: =IF(Input_Data!A9="","",Input_Data!A9) -> OPL | B9: =IF(Input_Data!B9="","",Input_Data!B9) -> Orange Polska | C9: =IF(Input_Data!C9="","",Input_Data!C9) -> Telecommunications | D9: =IF(OR(Input_Data!E9="",Input_Data!I9=""),"",Input_Data!E9*INDEX(Units!$C$5:$C$19,MATCH(Input_Data!$I9,Units!$A$5:$A$19,0))) -> 21538 | E9: =IF(OR(Input_Data!F9="",Input_Data!I9=""),"",Input_Data!F9*INDEX(Units!$C$5:$C$19,MATCH(Input_Data!$I9,Units!$A$5:$A$19,0))) -> 272838 | F9: =IF(OR(Input_Data!G9="",Input_Data!I9=""),"",Input_Data!G9*INDEX(Units!$C$5:$C$19,MATCH(Input_Data!$I9,Units!$A$5:$A$19,0))) -> 7354 | G9: =IF(OR(Input_Data!H9="",Input_Data!I9=""),"",Input_Data!H9*INDEX(Units!$C$5:$C$19,MATCH(Input_Data!$I9,Units!$A$5:$A$19,0))) -> 493158 | H9: =IF(OR(D9="",F9=""),"",D9+F9) -> 28892 | I9: =IF(OR(H9="",G9=""),"",H9+G9) -> 522050 | J9: =IF(OR(Input_Data!J9="",Input_Data!K9=""),"",Input_Data!J9*INDEX(Units!$C$5:$C$19,MATCH(Input_Data!$K9,Units!$A$5:$A$19,0))) -> 13133 | K9: =IF(OR(H9="",J9=""),"",H9/J9) -> 2.1999543 | L9: =IF(OR(I9="",J9=""),"",I9/J9) -> 39.751009 | M9: =IF(OR(H9="",Input_Data!L9=""),"",H9/Input_Data!L9) -> 3.535487 | N9: =IF(OR(G9="",I9=""),"",G9/I9) -> 0.94465664 | O9: =IF(OR(Input_Data!N9="",Input_Data!O9=""),"",Input_Data!N9*INDEX(Units!$C$5:$C$19,MATCH(Input_Data!$O9,Units!$A$5:$A$19,0))) -> 547748 | P9: =IF(OR(O9="",J9=""),"",O9/J9) -> 41.707759 | Q9: =IF(OR(Input_Data!P9="",Input_Data!Q9=""),"",Input_Data!P9*INDEX(Units!$C$5:$C$19,MATCH(Input_Data!$Q9,Units!$A$5:$A$19,0))) -> 40 | R9: =IF(OR(L9="",Q9=""),"",L9/Q9-1) -> -0.0062247773 | S9: =IF(Input_Data!R9="","",Input_Data!R9) -> 0 | T9: =IF(Input_Data!S9="","",Input_Data!S9) -> 0 | U9: =IF(Input_Data!T9="","",Input_Data!T9) -> 0
A10: =IF(Input_Data!A10="","",Input_Data!A10) -> ALE | B10: =IF(Input_Data!B10="","",Input_Data!B10) -> Allegro.eu | C10: =IF(Input_Data!C10="","",Input_Data!C10) -> E-commerce | D10: =IF(OR(Input_Data!E10="",Input_Data!I10=""),"",Input_Data!E10*INDEX(Units!$C$5:$C$19,MATCH(Input_Data!$I10,Units!$A$5:$A$19,0))) -> 1803 | E10: =IF(OR(Input_Data!F10="",Input_Data!I10=""),"",Input_Data!F10*INDEX(Units!$C$5:$C$19,MATCH(Input_Data!$I10,Units!$A$5:$A$19,0))) -> 17739 | F10: =IF(OR(Input_Data!G10="",Input_Data!I10=""),"",Input_Data!G10*INDEX(Units!$C$5:$C$19,MATCH(Input_Data!$I10,Units!$A$5:$A$19,0))) -> 4017 | G10: =IF(OR(Input_Data!H10="",Input_Data!I10=""),"",Input_Data!H10*INDEX(Units!$C$5:$C$19,MATCH(Input_Data!$I10,Units!$A$5:$A$19,0))) -> 419552 | H10: =IF(OR(D10="",F10=""),"",D10+F10) -> 5820 | I10: =IF(OR(H10="",G10=""),"",H10+G10) -> 425372 | J10: =IF(OR(Input_Data!J10="",Input_Data!K10=""),"",Input_Data!J10*INDEX(Units!$C$5:$C$19,MATCH(Input_Data!$K10,Units!$A$5:$A$19,0))) -> 11885.8 | K10: =IF(OR(H10="",J10=""),"",H10/J10) -> 0.48965993 | L10: =IF(OR(I10="",J10=""),"",I10/J10) -> 35.788252 | M10: =IF(OR(H10="",Input_Data!L10=""),"",H10/Input_Data!L10) -> 0.95566502 | N10: =IF(OR(G10="",I10=""),"",G10/I10) -> 0.98631786 | O10: =IF(OR(Input_Data!N10="",Input_Data!O10=""),"",Input_Data!N10*INDEX(Units!$C$5:$C$19,MATCH(Input_Data!$O10,Units!$A$5:$A$19,0))) -> 43603 | P10: =IF(OR(O10="",J10=""),"",O10/J10) -> 3.6684952 | Q10: =IF(OR(Input_Data!P10="",Input_Data!Q10=""),"",Input_Data!P10*INDEX(Units!$C$5:$C$19,MATCH(Input_Data!$Q10,Units!$A$5:$A$19,0))) -> 35.1 | R10: =IF(OR(L10="",Q10=""),"",L10/Q10-1) -> 0.019608306 | S10: =IF(Input_Data!R10="","",Input_Data!R10) -> 1e-05 | T10: =IF(Input_Data!S10="","",Input_Data!S10) -> 0.339 | U10: =IF(Input_Data!T10="","",Input_Data!T10) -> 0.404
A11: =IF(Input_Data!A11="","",Input_Data!A11) | B11: =IF(Input_Data!B11="","",Input_Data!B11) | C11: =IF(Input_Data!C11="","",Input_Data!C11) | D11: =IF(OR(Input_Data!E11="",Input_Data!I11=""),"",Input_Data!E11*INDEX(Units!$C$5:$C$19,MATCH(Input_Data!$I11,Units!$A$5:$A$19,0))) | E11: =IF(OR(Input_Data!F11="",Input_Data!I11=""),"",Input_Data!F11*INDEX(Units!$C$5:$C$19,MATCH(Input_Data!$I11,Units!$A$5:$A$19,0))) | F11: =IF(OR(Input_Data!G11="",Input_Data!I11=""),"",Input_Data!G11*INDEX(Units!$C$5:$C$19,MATCH(Input_Data!$I11,Units!$A$5:$A$19,0))) | G11: =IF(OR(Input_Data!H11="",Input_Data!I11=""),"",Input_Data!H11*INDEX(Units!$C$5:$C$19,MATCH(Input_Data!$I11,Units!$A$5:$A$19,0))) | H11: =IF(OR(D11="",F11=""),"",D11+F11) | I11: =IF(OR(H11="",G11=""),"",H11+G11) | J11: =IF(OR(Input_Data!J11="",Input_Data!K11=""),"",Input_Data!J11*INDEX(Units!$C$5:$C$19,MATCH(Input_Data!$K11,Units!$A$5:$A$19,0))) | K11: =IF(OR(H11="",J11=""),"",H11/J11) | L11: =IF(OR(I11="",J11=""),"",I11/J11) | M11: =IF(OR(H11="",Input_Data!L11=""),"",H11/Input_Data!L11) | N11: =IF(OR(G11="",I11=""),"",G11/I11) | O11: =IF(OR(Input_Data!N11="",Input_Data!O11=""),"",Input_Data!N11*INDEX(Units!$C$5:$C$19,MATCH(Input_Data!$O11,Units!$A$5:$A$19,0))) | P11: =IF(OR(O11="",J11=""),"",O11/J11) | Q11: =IF(OR(Input_Data!P11="",Input_Data!Q11=""),"",Input_Data!P11*INDEX(Units!$C$5:$C$19,MATCH(Input_Data!$Q11,Units!$A$5:$A$19,0))) | R11: =IF(OR(L11="",Q11=""),"",L11/Q11-1) | S11: =IF(Input_Data!R11="","",Input_Data!R11) | T11: =IF(Input_Data!S11="","",Input_Data!S11) | U11: =IF(Input_Data!T11="","",Input_Data!T11)
A12: =IF(Input_Data!A12="","",Input_Data!A12) | B12: =IF(Input_Data!B12="","",Input_Data!B12) | C12: =IF(Input_Data!C12="","",Input_Data!C12) | D12: =IF(OR(Input_Data!E12="",Input_Data!I12=""),"",Input_Data!E12*INDEX(Units!$C$5:$C$19,MATCH(Input_Data!$I12,Units!$A$5:$A$19,0))) | E12: =IF(OR(Input_Data!F12="",Input_Data!I12=""),"",Input_Data!F12*INDEX(Units!$C$5:$C$19,MATCH(Input_Data!$I12,Units!$A$5:$A$19,0))) | F12: =IF(OR(Input_Data!G12="",Input_Data!I12=""),"",Input_Data!G12*INDEX(Units!$C$5:$C$19,MATCH(Input_Data!$I12,Units!$A$5:$A$19,0))) | G12: =IF(OR(Input_Data!H12="",Input_Data!I12=""),"",Input_Data!H12*INDEX(Units!$C$5:$C$19,MATCH(Input_Data!$I12,Units!$A$5:$A$19,0))) | H12: =IF(OR(D12="",F12=""),"",D12+F12) | I12: =IF(OR(H12="",G12=""),"",H12+G12) | J12: =IF(OR(Input_Data!J12="",Input_Data!K12=""),"",Input_Data!J12*INDEX(Units!$C$5:$C$19,MATCH(Input_Data!$K12,Units!$A$5:$A$19,0))) | K12: =IF(OR(H12="",J12=""),"",H12/J12) | L12: =IF(OR(I12="",J12=""),"",I12/J12) | M12: =IF(OR(H12="",Input_Data!L12=""),"",H12/Input_Data!L12) | N12: =IF(OR(G12="",I12=""),"",G12/I12) | O12: =IF(OR(Input_Data!N12="",Input_Data!O12=""),"",Input_Data!N12*INDEX(Units!$C$5:$C$19,MATCH(Input_Data!$O12,Units!$A$5:$A$19,0))) | P12: =IF(OR(O12="",J12=""),"",O12/J12) | Q12: =IF(OR(Input_Data!P12="",Input_Data!Q12=""),"",Input_Data!P12*INDEX(Units!$C$5:$C$19,MATCH(Input_Data!$Q12,Units!$A$5:$A$19,0))) | R12: =IF(OR(L12="",Q12=""),"",L12/Q12-1) | S12: =IF(Input_Data!R12="","",Input_Data!R12) | T12: =IF(Input_Data!S12="","",Input_Data!S12) | U12: =IF(Input_Data!T12="","",Input_Data!T12)
A13: =IF(Input_Data!A13="","",Input_Data!A13) | B13: =IF(Input_Data!B13="","",Input_Data!B13) | C13: =IF(Input_Data!C13="","",Input_Data!C13) | D13: =IF(OR(Input_Data!E13="",Input_Data!I13=""),"",Input_Data!E13*INDEX(Units!$C$5:$C$19,MATCH(Input_Data!$I13,Units!$A$5:$A$19,0))) | E13: =IF(OR(Input_Data!F13="",Input_Data!I13=""),"",Input_Data!F13*INDEX(Units!$C$5:$C$19,MATCH(Input_Data!$I13,Units!$A$5:$A$19,0))) | F13: =IF(OR(Input_Data!G13="",Input_Data!I13=""),"",Input_Data!G13*INDEX(Units!$C$5:$C$19,MATCH(Input_Data!$I13,Units!$A$5:$A$19,0))) | G13: =IF(OR(Input_Data!H13="",Input_Data!I13=""),"",Input_Data!H13*INDEX(Units!$C$5:$C$19,MATCH(Input_Data!$I13,Units!$A$5:$A$19,0))) | H13: =IF(OR(D13="",F13=""),"",D13+F13) | I13: =IF(OR(H13="",G13=""),"",H13+G13) | J13: =IF(OR(Input_Data!J13="",Input_Data!K13=""),"",Input_Data!J13*INDEX(Units!$C$5:$C$19,MATCH(Input_Data!$K13,Units!$A$5:$A$19,0))) | K13: =IF(OR(H13="",J13=""),"",H13/J13) | L13: =IF(OR(I13="",J13=""),"",I13/J13) | M13: =IF(OR(H13="",Input_Data!L13=""),"",H13/Input_Data!L13) | N13: =IF(OR(G13="",I13=""),"",G13/I13) | O13: =IF(OR(Input_Data!N13="",Input_Data!O13=""),"",Input_Data!N13*INDEX(Units!$C$5:$C$19,MATCH(Input_Data!$O13,Units!$A$5:$A$19,0))) | P13: =IF(OR(O13="",J13=""),"",O13/J13) | Q13: =IF(OR(Input_Data!P13="",Input_Data!Q13=""),"",Input_Data!P13*INDEX(Units!$C$5:$C$19,MATCH(Input_Data!$Q13,Units!$A$5:$A$19,0))) | R13: =IF(OR(L13="",Q13=""),"",L13/Q13-1) | S13: =IF(Input_Data!R13="","",Input_Data!R13) | T13: =IF(Input_Data!S13="","",Input_Data!S13) | U13: =IF(Input_Data!T13="","",Input_Data!T13)

Sheet Data_Quality
A1: Automatic checks | H1: Tolerance for intensity check | I1: 0.05
A2: Company | B2: Missing core values | C2: Units complete | D2: Employee basis | E2: Period | F2: Intensity vs reported | G2: Status
A3: =IF(Input_Data!B2="","",Input_Data!B2) | B3: =IF(Input_Data!B2="","",(Input_Data!E2="")+(Input_Data!F2="")+(Input_Data!G2="")+(Input_Data!H2="")+(Input_Data!J2="")+(Input_Data!L2="")) | C3: =IF(Input_Data!B2="","",IF(AND(Input_Data!I2<>"",Input_Data!K2<>""),"OK","Unit missing")) | D3: =IF(Input_Data!B2="","",IF(Input_Data!M2="","Not stated",Input_Data!M2)) | E3: =IF(Input_Data!B2="","",IF(ISNUMBER(SEARCH("/",Input_Data!D2)),"Non-calendar FY","Calendar")) | F3: =IF(Input_Data!B2="","",IF(Calculations!R2="","No reported figure",IF(ABS(Calculations!R2)<=$I$1,"OK","CHECK"))) | G3: =IF(A3="","",IF(AND(B3=0,C3="OK",F3="OK"),"Validated","Review"))
A4: =IF(Input_Data!B3="","",Input_Data!B3) -> PGE Polska Grupa Energetyczna | B4: =IF(Input_Data!B3="","",(Input_Data!E3="")+(Input_Data!F3="")+(Input_Data!G3="")+(Input_Data!H3="")+(Input_Data!J3="")+(Input_Data!L3="")) -> 0 | C4: =IF(Input_Data!B3="","",IF(AND(Input_Data!I3<>"",Input_Data!K3<>""),"OK","Unit missing")) -> OK | D4: =IF(Input_Data!B3="","",IF(Input_Data!M3="","Not stated",Input_Data!M3)) -> Headcount | E4: =IF(Input_Data!B3="","",IF(ISNUMBER(SEARCH("/",Input_Data!D3)),"Non-calendar FY","Calendar")) -> Calendar | F4: =IF(Input_Data!B3="","",IF(Calculations!R3="","No reported figure",IF(ABS(Calculations!R3)<=$I$1,"OK","CHECK"))) -> OK | G4: =IF(A4="","",IF(AND(B4=0,C4="OK",F4="OK"),"Validated","Review")) -> Validated
A5: =IF(Input_Data!B4="","",Input_Data!B4) -> Tauron Polska Energia | B5: =IF(Input_Data!B4="","",(Input_Data!E4="")+(Input_Data!F4="")+(Input_Data!G4="")+(Input_Data!H4="")+(Input_Data!J4="")+(Input_Data!L4="")) -> 0 | C5: =IF(Input_Data!B4="","",IF(AND(Input_Data!I4<>"",Input_Data!K4<>""),"OK","Unit missing")) -> OK | D5: =IF(Input_Data!B4="","",IF(Input_Data!M4="","Not stated",Input_Data!M4)) -> Headcount | E5: =IF(Input_Data!B4="","",IF(ISNUMBER(SEARCH("/",Input_Data!D4)),"Non-calendar FY","Calendar")) -> Calendar | F5: =IF(Input_Data!B4="","",IF(Calculations!R4="","No reported figure",IF(ABS(Calculations!R4)<=$I$1,"OK","CHECK"))) -> OK | G5: =IF(A5="","",IF(AND(B5=0,C5="OK",F5="OK"),"Validated","Review")) -> Validated
A6: =IF(Input_Data!B5="","",Input_Data!B5) -> KGHM Polska Miedz | B6: =IF(Input_Data!B5="","",(Input_Data!E5="")+(Input_Data!F5="")+(Input_Data!G5="")+(Input_Data!H5="")+(Input_Data!J5="")+(Input_Data!L5="")) -> 0 | C6: =IF(Input_Data!B5="","",IF(AND(Input_Data!I5<>"",Input_Data!K5<>""),"OK","Unit missing")) -> OK | D6: =IF(Input_Data!B5="","",IF(Input_Data!M5="","Not stated",Input_Data!M5)) -> Headcount | E6: =IF(Input_Data!B5="","",IF(ISNUMBER(SEARCH("/",Input_Data!D5)),"Non-calendar FY","Calendar")) -> Calendar | F6: =IF(Input_Data!B5="","",IF(Calculations!R5="","No reported figure",IF(ABS(Calculations!R5)<=$I$1,"OK","CHECK"))) -> OK | G6: =IF(A6="","",IF(AND(B6=0,C6="OK",F6="OK"),"Validated","Review")) -> Validated
A7: =IF(Input_Data!B6="","",Input_Data!B6) -> Grupa Kety | B7: =IF(Input_Data!B6="","",(Input_Data!E6="")+(Input_Data!F6="")+(Input_Data!G6="")+(Input_Data!H6="")+(Input_Data!J6="")+(Input_Data!L6="")) -> 0 | C7: =IF(Input_Data!B6="","",IF(AND(Input_Data!I6<>"",Input_Data!K6<>""),"OK","Unit missing")) -> OK | D7: =IF(Input_Data!B6="","",IF(Input_Data!M6="","Not stated",Input_Data!M6)) -> Headcount | E7: =IF(Input_Data!B6="","",IF(ISNUMBER(SEARCH("/",Input_Data!D6)),"Non-calendar FY","Calendar")) -> Calendar | F7: =IF(Input_Data!B6="","",IF(Calculations!R6="","No reported figure",IF(ABS(Calculations!R6)<=$I$1,"OK","CHECK"))) -> No reported figure | G7: =IF(A7="","",IF(AND(B7=0,C7="OK",F7="OK"),"Validated","Review")) -> Review
A8: =IF(Input_Data!B7="","",Input_Data!B7) -> Grupa Zabka | B8: =IF(Input_Data!B7="","",(Input_Data!E7="")+(Input_Data!F7="")+(Input_Data!G7="")+(Input_Data!H7="")+(Input_Data!J7="")+(Input_Data!L7="")) -> 0 | C8: =IF(Input_Data!B7="","",IF(AND(Input_Data!I7<>"",Input_Data!K7<>""),"OK","Unit missing")) -> OK | D8: =IF(Input_Data!B7="","",IF(Input_Data!M7="","Not stated",Input_Data!M7)) -> Headcount | E8: =IF(Input_Data!B7="","",IF(ISNUMBER(SEARCH("/",Input_Data!D7)),"Non-calendar FY","Calendar")) -> Calendar | F8: =IF(Input_Data!B7="","",IF(Calculations!R7="","No reported figure",IF(ABS(Calculations!R7)<=$I$1,"OK","CHECK"))) -> OK | G8: =IF(A8="","",IF(AND(B8=0,C8="OK",F8="OK"),"Validated","Review")) -> Validated
A9: =IF(Input_Data!B8="","",Input_Data!B8) -> Dino Polska | B9: =IF(Input_Data!B8="","",(Input_Data!E8="")+(Input_Data!F8="")+(Input_Data!G8="")+(Input_Data!H8="")+(Input_Data!J8="")+(Input_Data!L8="")) -> 0 | C9: =IF(Input_Data!B8="","",IF(AND(Input_Data!I8<>"",Input_Data!K8<>""),"OK","Unit missing")) -> OK | D9: =IF(Input_Data!B8="","",IF(Input_Data!M8="","Not stated",Input_Data!M8)) -> Headcount | E9: =IF(Input_Data!B8="","",IF(ISNUMBER(SEARCH("/",Input_Data!D8)),"Non-calendar FY","Calendar")) -> Calendar | F9: =IF(Input_Data!B8="","",IF(Calculations!R8="","No reported figure",IF(ABS(Calculations!R8)<=$I$1,"OK","CHECK"))) -> OK | G9: =IF(A9="","",IF(AND(B9=0,C9="OK",F9="OK"),"Validated","Review")) -> Validated
A10: =IF(Input_Data!B9="","",Input_Data!B9) -> Orange Polska | B10: =IF(Input_Data!B9="","",(Input_Data!E9="")+(Input_Data!F9="")+(Input_Data!G9="")+(Input_Data!H9="")+(Input_Data!J9="")+(Input_Data!L9="")) -> 0 | C10: =IF(Input_Data!B9="","",IF(AND(Input_Data!I9<>"",Input_Data!K9<>""),"OK","Unit missing")) -> OK | D10: =IF(Input_Data!B9="","",IF(Input_Data!M9="","Not stated",Input_Data!M9)) -> Headcount | E10: =IF(Input_Data!B9="","",IF(ISNUMBER(SEARCH("/",Input_Data!D9)),"Non-calendar FY","Calendar")) -> Calendar | F10: =IF(Input_Data!B9="","",IF(Calculations!R9="","No reported figure",IF(ABS(Calculations!R9)<=$I$1,"OK","CHECK"))) -> OK | G10: =IF(A10="","",IF(AND(B10=0,C10="OK",F10="OK"),"Validated","Review")) -> Validated
A11: =IF(Input_Data!B10="","",Input_Data!B10) -> Allegro.eu | B11: =IF(Input_Data!B10="","",(Input_Data!E10="")+(Input_Data!F10="")+(Input_Data!G10="")+(Input_Data!H10="")+(Input_Data!J10="")+(Input_Data!L10="")) -> 0 | C11: =IF(Input_Data!B10="","",IF(AND(Input_Data!I10<>"",Input_Data!K10<>""),"OK","Unit missing")) -> OK | D11: =IF(Input_Data!B10="","",IF(Input_Data!M10="","Not stated",Input_Data!M10)) -> Headcount | E11: =IF(Input_Data!B10="","",IF(ISNUMBER(SEARCH("/",Input_Data!D10)),"Non-calendar FY","Calendar")) -> Calendar | F11: =IF(Input_Data!B10="","",IF(Calculations!R10="","No reported figure",IF(ABS(Calculations!R10)<=$I$1,"OK","CHECK"))) -> OK | G11: =IF(A11="","",IF(AND(B11=0,C11="OK",F11="OK"),"Validated","Review")) -> Validated
A12: =IF(Input_Data!B11="","",Input_Data!B11) | B12: =IF(Input_Data!B11="","",(Input_Data!E11="")+(Input_Data!F11="")+(Input_Data!G11="")+(Input_Data!H11="")+(Input_Data!J11="")+(Input_Data!L11="")) | C12: =IF(Input_Data!B11="","",IF(AND(Input_Data!I11<>"",Input_Data!K11<>""),"OK","Unit missing")) | D12: =IF(Input_Data!B11="","",IF(Input_Data!M11="","Not stated",Input_Data!M11)) | E12: =IF(Input_Data!B11="","",IF(ISNUMBER(SEARCH("/",Input_Data!D11)),"Non-calendar FY","Calendar")) | F12: =IF(Input_Data!B11="","",IF(Calculations!R11="","No reported figure",IF(ABS(Calculations!R11)<=$I$1,"OK","CHECK"))) | G12: =IF(A12="","",IF(AND(B12=0,C12="OK",F12="OK"),"Validated","Review"))
A13: =IF(Input_Data!B12="","",Input_Data!B12) | B13: =IF(Input_Data!B12="","",(Input_Data!E12="")+(Input_Data!F12="")+(Input_Data!G12="")+(Input_Data!H12="")+(Input_Data!J12="")+(Input_Data!L12="")) | C13: =IF(Input_Data!B12="","",IF(AND(Input_Data!I12<>"",Input_Data!K12<>""),"OK","Unit missing")) | D13: =IF(Input_Data!B12="","",IF(Input_Data!M12="","Not stated",Input_Data!M12)) | E13: =IF(Input_Data!B12="","",IF(ISNUMBER(SEARCH("/",Input_Data!D12)),"Non-calendar FY","Calendar")) | F13: =IF(Input_Data!B12="","",IF(Calculations!R12="","No reported figure",IF(ABS(Calculations!R12)<=$I$1,"OK","CHECK"))) | G13: =IF(A13="","",IF(AND(B13=0,C13="OK",F13="OK"),"Validated","Review"))
A14: =IF(Input_Data!B13="","",Input_Data!B13) | B14: =IF(Input_Data!B13="","",(Input_Data!E13="")+(Input_Data!F13="")+(Input_Data!G13="")+(Input_Data!H13="")+(Input_Data!J13="")+(Input_Data!L13="")) | C14: =IF(Input_Data!B13="","",IF(AND(Input_Data!I13<>"",Input_Data!K13<>""),"OK","Unit missing")) | D14: =IF(Input_Data!B13="","",IF(Input_Data!M13="","Not stated",Input_Data!M13)) | E14: =IF(Input_Data!B13="","",IF(ISNUMBER(SEARCH("/",Input_Data!D13)),"Non-calendar FY","Calendar")) | F14: =IF(Input_Data!B13="","",IF(Calculations!R13="","No reported figure",IF(ABS(Calculations!R13)<=$I$1,"OK","CHECK"))) | G14: =IF(A14="","",IF(AND(B14=0,C14="OK",F14="OK"),"Validated","Review"))
A17: Issue log
A18: Company | B18: Issue type | C18: Description | D18: Impact on comparability | E18: Resolution
A19: Dino Polska | B19: Methodology unclear | C19: Scope 2 market-based (207,858 t) higher than location-based (135,019 t): no guarantees of origin, residual mix factor 808.3 vs grid average 524.9 tCO2/GWh | D19: MB total higher than LB; not an error | E19: Kept both values; totals use MB
A20: Dino Polska | B20: Methodology unclear | C20: Scope 3 is 96.6% of total; category 1 (purchased goods) is spend-based using Climatiq factors. Company states high measurement uncertainty | D20: Intensity driven by an estimate | E20: Flagged in README
A21: Dino Polska | B21: Methodology unclear | C21: Location-based factor uses KOBIZE 2024 value for 2025 consumption (latest available) | D21: One-year lag in grid factor | E21: Noted, no adjustment
A22: Dino Polska | B22: Boundary or scope difference | C22: Taxonomy turnover KPI not assessed: eligible activities below 10% materiality threshold (Delegated Reg. 2026/73) | D22: 0% not comparable with companies that assessed the KPI | E22: Recorded as 0%, flagged
A23: Dino Polska | B23: Other | C23: No GHG reduction targets disclosed (E1-6 target columns empty, no formal transition plan in E1-1) | D23: Cannot assess progress against targets | E23: Noted in README
A24: Allegro.eu | B24: Boundary or scope difference | C24: Emissions include Mall South (Slovenia, Croatia; held for sale at 31.12.2025, SPA signed 7 Jan 2026). Its revenue (PLN 427.7m) sits in discontinued operations (note 18.2) and was added back to match the emissions boundary | D24: Continuing revenue only would overstate intensity by 5.8% | E24: Revenue = 11,458.1 + 427.7 = 11,885.8 PLN m
A25: Allegro.eu | B25: Methodology unclear | C25: Reported intensity (35.1) uses revenue plus other operating income incl. discontinued (PLN 12,103.4m). Net revenue only gives 35.8 (+2.0%) | D25: Reported intensity slightly understated vs strict net revenue | E25: Kept net revenue for consistency across companies
A26: Allegro.eu | B26: Restatement | C26: 2024 Scope 3 restated using primary supplier data; Polish Operations category 1 cut from 235,321 to 146,733 tCO2e | D26: 2024 comparatives in older reports not comparable | E26: Only 2025 used
A27: Allegro.eu | B27: Boundary or scope difference | C27: Report shows Group and Polish Operations separately; Group used. Non-Polish operations ~22% of market-based total | D27: Mixing boundaries would distort comparison | E27: Group boundary for all companies
A28: Allegro.eu | B28: Methodology unclear | C28: SBTi target -43% Scope 1+2 by 2030 described as vs 2024 in strategy text but vs 2021 base year elsewhere (14.2 kt matches 2021). 2025 MB Scope 1+2 (5.8 kt) already below 2030 level, driven by guarantees of origin (58% renewable); location-based Scope 1+2 is +35% vs 2021 | D28: Market-based progress relies on certificates, not lower consumption | E28: Flagged in README
A29: Orange Polska | B29: Unit inconsistency | C29: Intensity reported per PLN thousand and rounded to 2 decimals (0.04), i.e. 35-45 t per PLN m (+/-12%) | D29: Validation much less precise than for other companies | E29: Converted to t/PLN m; computed 39.75
... A58: Tauron Polska Energia | B58: Other | C58: Highest Taxonomy alignment in sample: turnover 38.8%, CapEx 84.5%, OpEx 74.2% (grids and renewables), despite 26.8 Mt total emissions. Intensity disclosed with 6 decimals (0.000807 t/PLN): precise, computed 806.8 matches | D58: Green investment coexists with coal generation (as for PGE) | E58: Noted in README
